BocalCrypter/BocalCrypter.py
BocalCrypter/__init__.py
BocalCrypter-1.2703.23.dist-info/LICENSE
BocalCrypter-1.2703.23.dist-info/METADATA
BocalCrypter-1.2703.23.dist-info/WHEEL
BocalCrypter-1.2703.23.dist-info/top_level.txt
BocalCrypter-1.2703.23.dist-info/RECORD
