Metadata-Version: 2.1
Name: BocalCrypter
Version: 1.2703.23
Summary: Easy encrypt of any data.
Author: JuanDiegoTorresInfante
Author-email: juandiegotorres35@gmail.com
Classifier: Programming Language :: Python :: 3
Classifier: License :: OSI Approved :: MIT License
Requires-Python: >=3.6
License-File: LICENSE
